pygsp2/__init__.py
pygsp2/features.py
pygsp2/graph_learning.py
pygsp2/learning.py
pygsp2/optimization.py
pygsp2/plotting.py
pygsp2/reduction.py
pygsp2/utils.py
pygsp2/utils_examples.py
pygsp2/data/readme_example_filter.png
pygsp2/data/readme_example_graph.png
pygsp2/data/pointclouds/airfoil.mat
pygsp2/data/pointclouds/bunny.mat
pygsp2/data/pointclouds/david500.mat
pygsp2/data/pointclouds/david64.mat
pygsp2/data/pointclouds/logogsp.mat
pygsp2/data/pointclouds/minnesota.mat
pygsp2/data/pointclouds/two_moons.mat
pygsp2/filters/__init__.py
pygsp2/filters/abspline.py
pygsp2/filters/approximations.py
pygsp2/filters/expwin.py
pygsp2/filters/filter.py
pygsp2/filters/gabor.py
pygsp2/filters/halfcosine.py
pygsp2/filters/heat.py
pygsp2/filters/held.py
pygsp2/filters/itersine.py
pygsp2/filters/mexicanhat.py
pygsp2/filters/meyer.py
pygsp2/filters/modulation.py
pygsp2/filters/papadakis.py
pygsp2/filters/rectangular.py
pygsp2/filters/regular.py
pygsp2/filters/simoncelli.py
pygsp2/filters/simpletight.py
pygsp2/filters/wave.py
pygsp2/graphs/__init__.py
pygsp2/graphs/_io.py
pygsp2/graphs/_layout.py
pygsp2/graphs/airfoil.py
pygsp2/graphs/barabasialbert.py
pygsp2/graphs/comet.py
pygsp2/graphs/community.py
pygsp2/graphs/davidsensornet.py
pygsp2/graphs/difference.py
pygsp2/graphs/erdosrenyi.py
pygsp2/graphs/fourier.py
pygsp2/graphs/fullconnected.py
pygsp2/graphs/graph.py
pygsp2/graphs/grid2d.py
pygsp2/graphs/linegraph.py
pygsp2/graphs/logo.py
pygsp2/graphs/lowstretchtree.py
pygsp2/graphs/minnesota.py
pygsp2/graphs/path.py
pygsp2/graphs/randomregular.py
pygsp2/graphs/randomring.py
pygsp2/graphs/ring.py
pygsp2/graphs/star.py
pygsp2/graphs/stochasticblockmodel.py
pygsp2/graphs/swissroll.py
pygsp2/graphs/torus.py
pygsp2/graphs/nngraphs/__init__.py
pygsp2/graphs/nngraphs/bunny.py
pygsp2/graphs/nngraphs/cube.py
pygsp2/graphs/nngraphs/grid2dimgpatches.py
pygsp2/graphs/nngraphs/imgpatches.py
pygsp2/graphs/nngraphs/nngraph.py
pygsp2/graphs/nngraphs/sensor.py
pygsp2/graphs/nngraphs/sphere.py
pygsp2-2.0.15.dist-info/METADATA
pygsp2-2.0.15.dist-info/WHEEL
pygsp2-2.0.15.dist-info/licenses/LICENSE.txt
pygsp2-2.0.15.dist-info/RECORD
