Metadata-Version: 2.3
Name: PyGSP2
Version: 2.0.15
Summary: Package for EEG Graph signal Processing
Project-URL: Homepage, https://github.com/gsp-eeg/PyGSP2
Project-URL: Issues, https://github.com/gsp-eeg/PyGSP2/issues
Author-email: Julio Rodino <jrodino14@gmail.com>, Alejandro Weinstein <alejandro.weinstein@gmail.com>, Andres Herrera <herrerandresc@gmail.com>, Camilo Jara <camilo.jara@ug.uchile.cl>, Lucas Cortés <lucascortesg@gmail.com>
License-File: LICENSE.txt
Classifier: License :: OSI Approved :: BSD License
Classifier: Operating System :: OS Independent
Classifier: Programming Language :: Python :: 3
Requires-Python: >=3.11
Requires-Dist: geopy
Requires-Dist: matplotlib
Requires-Dist: networkx
Requires-Dist: numpy
Requires-Dist: pandas
Requires-Dist: pyxlsb
Requires-Dist: scipy
Requires-Dist: unidecode
Requires-Dist: utm
